zapr/__init__.py
zapr/aws/Athena.py
zapr/aws/Glue.py
zapr/aws/__init__.py
zapr/aws/zaprs3client.py
zapr/utils/Utils.py
zapr/utils/__init__.py
zapr/utils/reader.py
zapr_athena_client-0.1.data/scripts/athena_client.py
zapr_athena_client-0.1.dist-info/LICENSE
zapr_athena_client-0.1.dist-info/METADATA
zapr_athena_client-0.1.dist-info/WHEEL
zapr_athena_client-0.1.dist-info/entry_points.txt
zapr_athena_client-0.1.dist-info/top_level.txt
zapr_athena_client-0.1.dist-info/RECORD
