Metadata-Version: 2.1
Name: zapr-athena-client
Version: 0.1
Summary: It is a python library to run the presto query on the AWS Athena.
Home-page: https://github.com/zapr-oss/zapr-athena-client
Author: ZAPR
Author-email: opensource@gzapr.in
License: UNKNOWN
Platform: UNKNOWN
Classifier: Programming Language :: Python :: 3
Classifier: License :: OSI Approved :: Apache Software License
Classifier: Operating System :: OS Independent
Requires-Dist: boto3 (==1.13.17)
Requires-Dist: botocore (==1.16.17)
